odoo/addons/stock_picking_date_deadline_syncs_scheduled_date/README.rst
odoo/addons/stock_picking_date_deadline_syncs_scheduled_date/__init__.py
odoo/addons/stock_picking_date_deadline_syncs_scheduled_date/__manifest__.py
odoo/addons/stock_picking_date_deadline_syncs_scheduled_date/i18n/it.po
odoo/addons/stock_picking_date_deadline_syncs_scheduled_date/i18n/stock_picking_date_deadline_syncs_scheduled_date.pot
odoo/addons/stock_picking_date_deadline_syncs_scheduled_date/models/__init__.py
odoo/addons/stock_picking_date_deadline_syncs_scheduled_date/models/stock_move.py
odoo/addons/stock_picking_date_deadline_syncs_scheduled_date/readme/CONTEXT.md
odoo/addons/stock_picking_date_deadline_syncs_scheduled_date/readme/CONTRIBUTORS.md
odoo/addons/stock_picking_date_deadline_syncs_scheduled_date/readme/DESCRIPTION.md
odoo/addons/stock_picking_date_deadline_syncs_scheduled_date/readme/ROADMAP.md
odoo/addons/stock_picking_date_deadline_syncs_scheduled_date/readme/USAGE.md
odoo/addons/stock_picking_date_deadline_syncs_scheduled_date/static/description/icon.png
odoo/addons/stock_picking_date_deadline_syncs_scheduled_date/static/description/index.html
odoo/addons/stock_picking_date_deadline_syncs_scheduled_date/tests/__init__.py
odoo/addons/stock_picking_date_deadline_syncs_scheduled_date/tests/test_date_deadline_sync.py
odoo_addon_stock_picking_date_deadline_syncs_scheduled_date-16.0.1.0.1.2.dist-info/METADATA
odoo_addon_stock_picking_date_deadline_syncs_scheduled_date-16.0.1.0.1.2.dist-info/WHEEL
odoo_addon_stock_picking_date_deadline_syncs_scheduled_date-16.0.1.0.1.2.dist-info/top_level.txt
odoo_addon_stock_picking_date_deadline_syncs_scheduled_date-16.0.1.0.1.2.dist-info/RECORD
